idbutils/__init__.py
idbutils/conversions.py
idbutils/csv_importer.py
idbutils/db.py
idbutils/db_attributes.py
idbutils/db_exception.py
idbutils/db_object.py
idbutils/derived_enum.py
idbutils/file_processor.py
idbutils/json_config.py
idbutils/json_file_processor.py
idbutils/key_value.py
idbutils/list_and_dict.py
idbutils/location.py
idbutils/open_with_app.py
idbutils/plugin.py
idbutils/rest_client.py
idbutils/version.py
idbutils/version_info.py
idbutils-1.0.8.dist-info/LICENSE
idbutils-1.0.8.dist-info/METADATA
idbutils-1.0.8.dist-info/WHEEL
idbutils-1.0.8.dist-info/top_level.txt
idbutils-1.0.8.dist-info/RECORD
